pyccoon/.DS_Store
pyccoon/.editorconfig
pyccoon/.pyccoon
pyccoon/__init__.py
pyccoon/markdown_extensions.py
pyccoon/pyccoon.py
pyccoon/pyccoon.svg
pyccoon/pyccoon_icon.svg
pyccoon/utils.py
pyccoon/languages/__init__.py
pyccoon/languages/utils.py
pyccoon/resources/.DS_Store
pyccoon/resources/__init__.py
pyccoon/resources/pycco.css
pyccoon/resources/pycco.html
pyccoon/resources/pyccoon.svg
pyccoon/resources/pyccoon_icon.svg
pyccoon-0.1.0.dist-info/DESCRIPTION.rst
pyccoon-0.1.0.dist-info/entry_points.txt
pyccoon-0.1.0.dist-info/METADATA
pyccoon-0.1.0.dist-info/metadata.json
pyccoon-0.1.0.dist-info/RECORD
pyccoon-0.1.0.dist-info/top_level.txt
pyccoon-0.1.0.dist-info/WHEEL
