Metadata-Version: 2.0
Name: pyccoon
Version: 0.1.0
Summary: Side-to-side documentation generator, a descendant of Pycco and Docco.
Home-page: https://github.com/ckald/pyccoon
Author: Andrii Magalich
Author-email: andrew.magalich@gmail.com
License: MIT
Keywords: pyccoon
Platform: UNKNOWN
Classifier: Development Status :: 2 - Pre-Alpha
Classifier: Intended Audience :: Developers
Classifier: License :: OSI Approved :: MIT License
Classifier: Natural Language :: English
Classifier: Programming Language :: Python :: 2
Classifier: Programming Language :: Python :: 2.6
Classifier: Programming Language :: Python :: 2.7
Classifier: Programming Language :: Python :: 3
Classifier: Programming Language :: Python :: 3.3
Classifier: Programming Language :: Python :: 3.4
Classifier: Programming Language :: Python :: Implementation :: PyPy
Requires-Dist: wheel (==0.23.0)
Requires-Dist: pystache (==0.5.4)
Requires-Dist: markdown (==2.4.1)
Requires-Dist: Pygments (==1.6)
